mcp_cli/__init__.py
mcp_cli/__main__.py
mcp_cli/async_config.py
mcp_cli/constants.py
mcp_cli/logging_config.py
mcp_cli/main.py
mcp_cli/model_manager.py
mcp_cli/run_command.py
mcp_cli/server_config.json
mcp_cli/adapters/chat.py
mcp_cli/adapters/cli.py
mcp_cli/adapters/interactive.py
mcp_cli/auth/__init__.py
mcp_cli/auth/provider_tokens.py
mcp_cli/chat/__init__.py
mcp_cli/chat/__main__.py
mcp_cli/chat/chat_context.py
mcp_cli/chat/chat_handler.py
mcp_cli/chat/command_completer.py
mcp_cli/chat/conversation.py
mcp_cli/chat/streaming_handler.py
mcp_cli/chat/system_prompt.py
mcp_cli/chat/tool_processor.py
mcp_cli/chat/ui_manager.py
mcp_cli/chat/commands/__init__.py
mcp_cli/cli/__init__.py
mcp_cli/cli/commands/__init__.py
mcp_cli/commands/__init__.py
mcp_cli/commands/base.py
mcp_cli/commands/decorators.py
mcp_cli/commands/exceptions.py
mcp_cli/commands/registry.py
mcp_cli/commands/types.py
mcp_cli/commands/utils.py
mcp_cli/commands/actions/__init__.py
mcp_cli/commands/actions/clear.py
mcp_cli/commands/actions/cmd.py
mcp_cli/commands/actions/exit.py
mcp_cli/commands/actions/help.py
mcp_cli/commands/actions/models.py
mcp_cli/commands/actions/ping.py
mcp_cli/commands/actions/prompts.py
mcp_cli/commands/actions/providers.py
mcp_cli/commands/actions/resources.py
mcp_cli/commands/actions/servers.py
mcp_cli/commands/actions/theme.py
mcp_cli/commands/actions/token.py
mcp_cli/commands/actions/tools.py
mcp_cli/commands/actions/tools_call.py
mcp_cli/commands/actions/tools_confirm.py
mcp_cli/commands/actions/tools_manage.py
mcp_cli/commands/definitions/__init__.py
mcp_cli/commands/definitions/clear.py
mcp_cli/commands/definitions/conversation.py
mcp_cli/commands/definitions/execute_tool.py
mcp_cli/commands/definitions/exit.py
mcp_cli/commands/definitions/help.py
mcp_cli/commands/definitions/interrupt.py
mcp_cli/commands/definitions/models.py
mcp_cli/commands/definitions/ping.py
mcp_cli/commands/definitions/prompts.py
mcp_cli/commands/definitions/provider_singular.py
mcp_cli-0.10.1.dist-info/METADATA
mcp_cli-0.10.1.dist-info/WHEEL
mcp_cli-0.10.1.dist-info/entry_points.txt
mcp_cli-0.10.1.dist-info/top_level.txt
mcp_cli-0.10.1.dist-info/RECORD
