Metadata-Version: 2.4
Name: mcp-cli
Version: 0.10.1
Summary: A cli for the Model Context Provider
Author-email: Chris Hay <chrishayuk@somejunkmailbox.com>
License: MIT
Keywords: llm,openai,claude,mcp,cli
Requires-Python: >=3.11
Requires-Dist: asyncio>=3.4.3
Requires-Dist: chuk-llm[all]>=0.12.7
Requires-Dist: chuk-mcp-client-oauth>=0.3.5
Requires-Dist: chuk-term>=0.1.3
Requires-Dist: chuk-tool-processor==0.9.7
Requires-Dist: cryptography>=44.0.0
Requires-Dist: httpx>=0.27.0
Requires-Dist: jsonschema>=4.25.1
Requires-Dist: keyring>=25.0.0
Requires-Dist: prompt-toolkit>=3.0.50
Requires-Dist: python-dotenv>=1.0.1
Requires-Dist: rich>=13.9.4
Requires-Dist: typer>=0.15.2
Provides-Extra: vault
Requires-Dist: hvac>=2.0.0; extra == "vault"
Provides-Extra: wasm
Provides-Extra: dev
Requires-Dist: numpy>=2.2.3; extra == "dev"
Requires-Dist: pytest-asyncio>=0.25.3; extra == "dev"
Requires-Dist: asyncio>=3.4.3; extra == "dev"
